{"hat_no": 684, "timestamp": "2026-06-28T08:57:27.004051+03:00", "timestamp_unix": 1782626247, "buses_on_route": [{"OtobusId": 9054, "Yon": 0, "KoorY": "27,14469833", "KoorX": "38,352815", "hareket_metre": null, "hiz_kmh": null, "gps_lag": false, "trafik_kume": 0}, {"OtobusId": 9059, "Yon": 1, "KoorY": "26,95016833", "KoorX": "38,388715", "hareket_metre": null, "hiz_kmh": null, "gps_lag": false, "trafik_kume": 0}, {"OtobusId": 9071, "Yon": 1, "KoorY": "26,75516333", "KoorX": "38,32666167", "hareket_metre": null, "hiz_kmh": null, "gps_lag": false, "trafik_kume": 0}, {"OtobusId": 11039, "Yon": 0, "KoorY": "26,76285", "KoorX": "38,32157833", "hareket_metre": null, "hiz_kmh": null, "gps_lag": false, "trafik_kume": 0}, {"OtobusId": 30011, "Yon": 0, "KoorY": "27,06656333", "KoorX": "38,398275", "hareket_metre": null, "hiz_kmh": null, "gps_lag": false, "trafik_kume": 0}], "approaching": {"baslangic_gidis": [{"KalanDurakSayisi": 6, "HattinYonu": 2, "KoorY": "26,76065333", "BisikletAparatliMi": false, "KoorX": "38,3213", "EngelliMi": false, "HatNumarasi": 684, "HatAdi": "F.ALTAY - URLA (EKSPRES)", "OtobusId": 13109}, {"KalanDurakSayisi": 6, "HattinYonu": 2, "KoorY": "26,76065333", "BisikletAparatliMi": false, "KoorX": "38,3213", "EngelliMi": false, "HatNumarasi": 684, "HatAdi": "F.ALTAY - URLA (EKSPRES)", "OtobusId": 13108}, {"KalanDurakSayisi": 6, "HattinYonu": 2, "KoorY": "26,76042833", "BisikletAparatliMi": false, "KoorX": "38,32128833", "EngelliMi": false, "HatNumarasi": 684, "HatAdi": "F.ALTAY - URLA (EKSPRES)", "OtobusId": 11039}, {"KalanDurakSayisi": 7, "HattinYonu": 2, "KoorY": "26,76180667", "BisikletAparatliMi": false, "KoorX": "38,32144167", "EngelliMi": false, "HatNumarasi": 684, "HatAdi": "F.ALTAY - URLA (EKSPRES)", "OtobusId": 13110}, {"KalanDurakSayisi": 16, "HattinYonu": 2, "KoorY": "27,06655667", "BisikletAparatliMi": false, "KoorX": "38,39831", "EngelliMi": false, "HatNumarasi": 684, "HatAdi": "F.ALTAY - URLA (EKSPRES)", "OtobusId": 31123}, {"KalanDurakSayisi": 16, "HattinYonu": 2, "KoorY": "27,06656333", "BisikletAparatliMi": false, "KoorX": "38,398275", "EngelliMi": false, "HatNumarasi": 684, "HatAdi": "F.ALTAY - URLA (EKSPRES)", "OtobusId": 30011}, {"KalanDurakSayisi": 16, "HattinYonu": 2, "KoorY": "27,06655667", "BisikletAparatliMi": false, "KoorX": "38,39831", "EngelliMi": false, "HatNumarasi": 684, "HatAdi": "F.ALTAY - URLA (EKSPRES)", "OtobusId": 31124}, {"KalanDurakSayisi": 16, "HattinYonu": 2, "KoorY": "27,06655667", "BisikletAparatliMi": false, "KoorX": "38,39831", "EngelliMi": false, "HatNumarasi": 684, "HatAdi": "F.ALTAY - URLA (EKSPRES)", "OtobusId": 31125}, {"KalanDurakSayisi": 16, "HattinYonu": 2, "KoorY": "27,14482333", "BisikletAparatliMi": false, "KoorX": "38,35279333", "EngelliMi": false, "HatNumarasi": 684, "HatAdi": "F.ALTAY - URLA (EKSPRES)", "OtobusId": 9561}, {"KalanDurakSayisi": 16, "HattinYonu": 2, "KoorY": "27,14482333", "BisikletAparatliMi": false, "KoorX": "38,35279333", "EngelliMi": false, "HatNumarasi": 684, "HatAdi": "F.ALTAY - URLA (EKSPRES)", "OtobusId": 9560}, {"KalanDurakSayisi": 16, "HattinYonu": 2, "KoorY": "27,14469833", "BisikletAparatliMi": false, "KoorX": "38,352815", "EngelliMi": false, "HatNumarasi": 684, "HatAdi": "F.ALTAY - URLA (EKSPRES)", "OtobusId": 9054}], "baslangic_donus": []}, "gps_lag_araclar": [], "trafik_alanlari": []}