{"hat_no": 684, "timestamp": "2026-06-27T16:22:44.608893+03:00", "timestamp_unix": 1782566564, "buses_on_route": [{"OtobusId": 9057, "Yon": 0, "KoorY": "26,74868", "KoorX": "38,32782667", "hareket_metre": null, "hiz_kmh": null, "gps_lag": false, "trafik_kume": 0}, {"OtobusId": 9060, "Yon": 0, "KoorY": "27,066995", "KoorX": "38,39817667", "hareket_metre": null, "hiz_kmh": null, "gps_lag": false, "trafik_kume": 0}, {"OtobusId": 9071, "Yon": 0, "KoorY": "26,86416333", "KoorX": "38,37348833", "hareket_metre": null, "hiz_kmh": null, "gps_lag": false, "trafik_kume": 0}], "approaching": {"baslangic_gidis": [{"KalanDurakSayisi": 2, "HattinYonu": 2, "KoorY": "26,74818333", "BisikletAparatliMi": false, "KoorX": "38,32954833", "EngelliMi": false, "HatNumarasi": 684, "HatAdi": "F.ALTAY - URLA (EKSPRES)", "OtobusId": 9571}, {"KalanDurakSayisi": 2, "HattinYonu": 2, "KoorY": "26,74868", "BisikletAparatliMi": false, "KoorX": "38,32782667", "EngelliMi": false, "HatNumarasi": 684, "HatAdi": "F.ALTAY - URLA (EKSPRES)", "OtobusId": 9570}, {"KalanDurakSayisi": 2, "HattinYonu": 2, "KoorY": "26,74868", "BisikletAparatliMi": false, "KoorX": "38,32782667", "EngelliMi": false, "HatNumarasi": 684, "HatAdi": "F.ALTAY - URLA (EKSPRES)", "OtobusId": 9569}, {"KalanDurakSayisi": 2, "HattinYonu": 2, "KoorY": "26,74868", "BisikletAparatliMi": false, "KoorX": "38,32782667", "EngelliMi": false, "HatNumarasi": 684, "HatAdi": "F.ALTAY - URLA (EKSPRES)", "OtobusId": 9057}, {"KalanDurakSayisi": 15, "HattinYonu": 2, "KoorY": "26,86416333", "BisikletAparatliMi": false, "KoorX": "38,37348833", "EngelliMi": false, "HatNumarasi": 684, "HatAdi": "F.ALTAY - URLA (EKSPRES)", "OtobusId": 9071}, {"KalanDurakSayisi": 15, "HattinYonu": 2, "KoorY": "26,87406333", "BisikletAparatliMi": false, "KoorX": "38,36706667", "EngelliMi": false, "HatNumarasi": 684, "HatAdi": "F.ALTAY - URLA (EKSPRES)", "OtobusId": 9201}, {"KalanDurakSayisi": 15, "HattinYonu": 2, "KoorY": "26,87404667", "BisikletAparatliMi": false, "KoorX": "38,36698333", "EngelliMi": false, "HatNumarasi": 684, "HatAdi": "F.ALTAY - URLA (EKSPRES)", "OtobusId": 9200}, {"KalanDurakSayisi": 15, "HattinYonu": 2, "KoorY": "26,87406333", "BisikletAparatliMi": false, "KoorX": "38,36706667", "EngelliMi": false, "HatNumarasi": 684, "HatAdi": "F.ALTAY - URLA (EKSPRES)", "OtobusId": 9202}, {"KalanDurakSayisi": 16, "HattinYonu": 2, "KoorY": "27,06697833", "BisikletAparatliMi": false, "KoorX": "38,39853", "EngelliMi": false, "HatNumarasi": 684, "HatAdi": "F.ALTAY - URLA (EKSPRES)", "OtobusId": 9580}, {"KalanDurakSayisi": 16, "HattinYonu": 2, "KoorY": "27,066225", "BisikletAparatliMi": false, "KoorX": "38,39803667", "EngelliMi": false, "HatNumarasi": 684, "HatAdi": "F.ALTAY - URLA (EKSPRES)", "OtobusId": 9578}, {"KalanDurakSayisi": 16, "HattinYonu": 2, "KoorY": "27,066995", "BisikletAparatliMi": false, "KoorX": "38,39817667", "EngelliMi": false, "HatNumarasi": 684, "HatAdi": "F.ALTAY - URLA (EKSPRES)", "OtobusId": 9060}, {"KalanDurakSayisi": 16, "HattinYonu": 2, "KoorY": "27,06697833", "BisikletAparatliMi": false, "KoorX": "38,39853", "EngelliMi": false, "HatNumarasi": 684, "HatAdi": "F.ALTAY - URLA (EKSPRES)", "OtobusId": 9579}], "baslangic_donus": []}, "gps_lag_araclar": [], "trafik_alanlari": []}